configs/__init__.py
configs/deepspeed/zero3_config_gpu1.json
configs/deepspeed/zero3_config_gpu2.json
configs/deepspeed/zero3_config_gpu4.json
configs/deepspeed/zero3_config_gpu8.json
core/__init__.py
core/config.py
core/model_utils.py
core/trainer_base.py
evaluations/README.md
evaluations/__init__.py
evaluations/eval.py
evaluations/eval_datasets/__init__.py
evaluations/eval_datasets/gsm8k.py
evaluations/eval_datasets/mmlu.py
fai_rl-0.1.13.dist-info/licenses/LICENSE
inference/README.md
inference/__init__.py
inference/inference.py
recipes/__init__.py
recipes/evaluation/gsm8k/llama3_3B_vanilla.yaml
recipes/evaluation/gsm8k/llama3_8B_vanilla.yaml
recipes/evaluation/gsm8k/qwen3_4B.yaml
recipes/evaluation/gsm8k/qwen3_4B_multi_ckpt.yaml
recipes/evaluation/gsm8k/qwen3_4B_vanilla.yaml
recipes/evaluation/gsm8k/qwen3_8B_vanilla.yaml
recipes/evaluation/mmlu/llama3_3B.yaml
recipes/evaluation/mmlu/llama3_3B_api.yaml
recipes/evaluation/mmlu/llama3_3B_multi_ckpt.yaml
recipes/evaluation/mmlu/llama3_vanilla_3B.yaml
recipes/inference/llama3_3B.yaml
recipes/inference/llama3_3B_api.yaml
recipes/inference/llama3_3B_local_csv.yaml
recipes/inference/llama3_3B_multi_ckpt.yaml
recipes/inference/llama3_vanilla_3B.yaml
recipes/inference/robloxguard.yaml
recipes/training/dpo/llama3_3B_full.yaml
recipes/training/dpo/llama3_3B_lora.yaml
recipes/training/dpo/llama3_3B_qlora.yaml
recipes/training/grpo/llama3_3B_full.yaml
recipes/training/grpo/llama3_3B_lora.yaml
recipes/training/gspo/llama3_3B_full.yaml
recipes/training/gspo/llama3_3B_lora.yaml
recipes/training/ppo/llama3_3B_full.yaml
recipes/training/ppo/llama3_3B_lora.yaml
recipes/training/ppo/llama3_3B_qlora.yaml
recipes/training/sft/llama3_3B_full.yaml
recipes/training/sft/llama3_3B_lora.yaml
recipes/training/sft/llama3_3B_qlora.yaml
trainers/README.md
trainers/__init__.py
trainers/dpo_trainer.py
trainers/grpo_trainer.py
trainers/gspo_trainer.py
trainers/ppo_trainer.py
trainers/sft_trainer.py
trainers/train.py
trainers/rewards/__init__.py
trainers/rewards/accuracy_rewards.py
fai_rl-0.1.13.dist-info/METADATA
fai_rl-0.1.13.dist-info/WHEEL
fai_rl-0.1.13.dist-info/entry_points.txt
fai_rl-0.1.13.dist-info/top_level.txt
fai_rl-0.1.13.dist-info/RECORD
