Metadata-Version: 2.4
Name: FAI-RL
Version: 0.1.13
Summary: Foundation of AI - Reinforcement learning Library
Author-email: Roblox <ylim@roblox.com>, Roblox <mnandwana@roblox.com>
License-Expression: MIT
Project-URL: Homepage, https://github.com/Roblox/FAI-RL
Project-URL: Documentation, https://github.com/Roblox/FAI-RL#readme
Project-URL: Repository, https://github.com/Roblox/FAI-RL
Project-URL: Issues, https://github.com/Roblox/FAI-RL/issues
Keywords: reinforcement learning,language models,transformers,rlhf,dpo,ppo,sft
Classifier: Development Status :: 4 - Beta
Classifier: Intended Audience :: Developers
Classifier: Intended Audience :: Science/Research
Classifier: Programming Language :: Python :: 3
Classifier: Programming Language :: Python :: 3.8
Classifier: Programming Language :: Python :: 3.9
Classifier: Programming Language :: Python :: 3.10
Classifier: Programming Language :: Python :: 3.11
Classifier: Topic :: Scientific/Engineering :: Artificial Intelligence
Classifier: Topic :: Software Development :: Libraries :: Python Modules
Requires-Python: >=3.8
License-File: LICENSE
Requires-Dist: torch==2.7.1
Requires-Dist: torchvision==0.22.1
Requires-Dist: torchaudio==2.7.1
Requires-Dist: datasets==4.0.0
Requires-Dist: transformers==4.56.1
Requires-Dist: trl==0.23.0
Requires-Dist: wandb==0.21.0
Requires-Dist: peft==0.17.0
Requires-Dist: ipykernel==6.30.1
Requires-Dist: ipywidgets==8.1.7
Requires-Dist: fsspec==2025.3.0
Requires-Dist: huggingface_hub==0.34.4
Requires-Dist: tiktoken==0.12.0
Provides-Extra: cuda
Requires-Dist: bitsandbytes==0.46.1; extra == "cuda"
Requires-Dist: deepspeed==0.17.4; extra == "cuda"
Requires-Dist: mpi4py==4.1.0; extra == "cuda"
Provides-Extra: dev
Requires-Dist: pytest>=7.0.0; extra == "dev"
Requires-Dist: black>=22.0.0; extra == "dev"
Requires-Dist: flake8>=4.0.0; extra == "dev"
Requires-Dist: mypy>=0.950; extra == "dev"
Dynamic: license-file
